qcodes_loop/__init__.py
qcodes_loop/_version.py
qcodes_loop/actions.py
qcodes_loop/loops.py
qcodes_loop/measure.py
qcodes_loop/py.typed
qcodes_loop/data/__init__.py
qcodes_loop/data/data_array.py
qcodes_loop/data/data_set.py
qcodes_loop/data/format.py
qcodes_loop/data/gnuplot_format.py
qcodes_loop/data/hdf5_format.py
qcodes_loop/data/hdf5_format_hickle.py
qcodes_loop/data/io.py
qcodes_loop/data/location.py
qcodes_loop/extensions/__init__.py
qcodes_loop/extensions/slack.py
qcodes_loop/plots/__init__.py
qcodes_loop/plots/base.py
qcodes_loop/plots/colors.py
qcodes_loop/plots/pyqtgraph.py
qcodes_loop/plots/qcmatplotlib.py
qcodes_loop/tests/__init__.py
qcodes_loop/tests/common.py
qcodes_loop/tests/data_mocks.py
qcodes_loop/tests/test_channels.py
qcodes_loop/tests/test_combined_loop.py
qcodes_loop/tests/test_data.py
qcodes_loop/tests/test_format.py
qcodes_loop/tests/test_generic_formatter.py
qcodes_loop/tests/test_hdf5formatter.py
qcodes_loop/tests/test_location_provider.py
qcodes_loop/tests/test_loop.py
qcodes_loop/tests/test_measure.py
qcodes_loop/tests/test_plots.py
qcodes_loop/tests/test_qcmatplotlib_functions.py
qcodes_loop/tests/test_slack.py
qcodes_loop/tests/test_threading.py
qcodes_loop/tests/test_waitsecs.py
qcodes_loop/utils/__init__.py
qcodes_loop/utils/magic.py
qcodes_loop/utils/qt_helpers.py
qcodes_loop-0.1.3.dist-info/LICENSE
qcodes_loop-0.1.3.dist-info/METADATA
qcodes_loop-0.1.3.dist-info/WHEEL
qcodes_loop-0.1.3.dist-info/top_level.txt
qcodes_loop-0.1.3.dist-info/RECORD
